{"id":"decimal","path":"/home/zolii/Desktop/pyqt5-library-mvc-2.8.5./pyqt5-library-mvc-2.8.0/venv/lib/python3.13/site-packages/mypy/typeshed/stdlib/decimal.pyi","mtime":1755873325,"size":117,"hash":"3af726e9b7292d9cb1396aeb99d9d991d615541e03459cf2265298543cb29e69","data_mtime":1755870235,"dependencies":["_decimal","builtins","abc","importlib","importlib.machinery","typing"],"suppressed":[],"options":{"local_partial_types":false,"ignore_errors":false,"ignore_missing_imports":true,"old_type_inference":false,"disallow_subclassing_any":false,"follow_imports":"normal","always_true":[],"plugins":[],"disallow_untyped_calls":false,"disallow_any_unimported":false,"warn_unused_ignores":false,"strict_concatenate":false,"implicit_reexport":true,"disabled_error_codes":[],"platform":"linux","disallow_incomplete_defs":false,"disable_error_code":[],"disable_bytearray_promotion":false,"warn_return_any":false,"disallow_any_explicit":false,"extra_checks":false,"allow_redefinition":false,"strict_equality":false,"enabled_error_codes":[],"mypyc":false,"enable_error_code":[],"disallow_any_expr":false,"disallow_untyped_defs":true,"follow_imports_for_stubs":false,"disallow_untyped_decorators":false,"allow_untyped_globals":false,"strict_optional":true,"bazel":false,"disable_memoryview_promotion":false,"implicit_optional":false,"disallow_any_decorated":false,"warn_no_return":true,"disallow_any_generics":false,"warn_unreachable":false,"check_untyped_defs":true,"always_false":[]},"dep_prios":[5,5,30,30,30,30],"dep_lines":[1,1,1,1,1,1],"interface_hash":"1d02d7abf689b3d878f1525a4038f71e14c75629eb4f872d77ae5a4042d7c381","version_id":"1.11.2","ignore_all":true,"plugin_data":null}